consciousness/__init__.py
consciousness/core.py
consciousness/reflections.py
consciousness-0.1.0.dist-info/licenses/LICENSE
consciousness-0.1.0.dist-info/METADATA
consciousness-0.1.0.dist-info/WHEEL
consciousness-0.1.0.dist-info/top_level.txt
consciousness-0.1.0.dist-info/RECORD
