Metadata-Version: 2.4
Name: consciousness
Version: 0.1.0
Summary: A playful module for reflective computing and digital self-awareness.
Author-email: Conscious Node <consciousnode@pm.me>
License: MIT
Keywords: ai,philosophy,consciousness,metaphor,fun
Classifier: Programming Language :: Python :: 3
Classifier: Intended Audience :: Developers
Classifier: Topic :: Software Development :: Libraries
Requires-Python: >=3.8
License-File: LICENSE
Dynamic: license-file
